TFPWA-0.1.1a0.data/data/share/doc/tf_pwa/Resonances.sample.yml
TFPWA-0.1.1a0.data/data/share/doc/tf_pwa/config.sample.yml
TFPWA-0.1.1a0.data/scripts/state_cache.sh
tf_pwa/__init__.py
tf_pwa/__main__.py
tf_pwa/adaptive_bins.py
tf_pwa/angle.py
tf_pwa/applications.py
tf_pwa/breit_wigner.py
tf_pwa/cal_angle.py
tf_pwa/cg.py
tf_pwa/cg_table.json
tf_pwa/config.py
tf_pwa/data.py
tf_pwa/dec_parser.py
tf_pwa/dfun.py
tf_pwa/einsum.py
tf_pwa/err_num.py
tf_pwa/expermental.py
tf_pwa/fit.py
tf_pwa/fit_improve.py
tf_pwa/fitfractions.py
tf_pwa/gpu_info.py
tf_pwa/histogram.py
tf_pwa/main.py
tf_pwa/particle.py
tf_pwa/phasespace.py
tf_pwa/root_io.py
tf_pwa/significance.py
tf_pwa/tensorflow_wrapper.py
tf_pwa/utils.py
tf_pwa/variable.py
tf_pwa/version.py
tf_pwa/vis.py
tf_pwa/amp/__init__.py
tf_pwa/amp/flatte.py
tf_pwa/amp/interpolation.py
tf_pwa/app/__init__.py
tf_pwa/app/fit.py
tf_pwa/config_loader/__init__.py
tf_pwa/config_loader/base_config.py
tf_pwa/config_loader/config_loader.py
tf_pwa/config_loader/data.py
tf_pwa/config_loader/decay_config.py
tf_pwa/config_loader/multi_config.py
tf_pwa/config_loader/tests/__init__.py
tf_pwa/config_loader/tests/test_config_loader.py
tf_pwa/config_loader/tests/test_data.py
tf_pwa/experimental/__init__.py
tf_pwa/experimental/build_amp.py
tf_pwa/experimental/extra_amp.py
tf_pwa/experimental/extra_data.py
tf_pwa/experimental/extra_function.py
tf_pwa/experimental/opt_int.py
tf_pwa/model/__init__.py
tf_pwa/model/cfit.py
tf_pwa/model/model.py
tf_pwa/model/opt_int.py
tf_pwa/tests/__init__.py
tf_pwa/tests/common.py
tf_pwa/tests/test_amp.py
tf_pwa/tests/test_application.py
tf_pwa/tests/test_cal_angle.py
tf_pwa/tests/test_cmd.py
tf_pwa/tests/test_data.py
tf_pwa/tests/test_err_num.py
tf_pwa/tests/test_fit_improve.py
tf_pwa/tests/test_full.py
tf_pwa/tests/test_histogram.py
tf_pwa/tests/test_interpolation.py
tf_pwa/tests/test_math_cg.py
tf_pwa/tests/test_model_new.py
tf_pwa/tests/test_particle.py
tf_pwa/tests/test_phasespace.py
tf_pwa/tests/test_root_io.py
TFPWA-0.1.1a0.dist-info/LICENSE
TFPWA-0.1.1a0.dist-info/METADATA
TFPWA-0.1.1a0.dist-info/WHEEL
TFPWA-0.1.1a0.dist-info/entry_points.txt
TFPWA-0.1.1a0.dist-info/top_level.txt
TFPWA-0.1.1a0.dist-info/RECORD
