Metadata-Version: 2.1
Name: TFPWA
Version: 0.1.1a0
Summary: Partial Wave Analysis program using Tensorflow
Home-page: https://github.com/jiangyi15/tf-pwa
Author: Yi Jiang
Author-email: jiangyi15@mails.ucas.ac.cn
License: MIT
Project-URL: Documentation, https://tf-pwa.readthedocs.io/en/latest
Project-URL: Source, https://github.com/jiangyi15/tf-pwa
Project-URL: Tracker, https://github.com/jiangyi15/tf-pwa/issues
Keywords: HEP,PWA,particle physics,physics
Platform: UNKNOWN
Classifier: Development Status :: 3 - Alpha
Classifier: Intended Audience :: Developers
Classifier: Intended Audience :: Science/Research
Classifier: License :: OSI Approved :: MIT License
Classifier: Natural Language :: English
Classifier: Operating System :: OS Independent
Classifier: Programming Language :: Python
Classifier: Programming Language :: Python :: 3.6
Classifier: Programming Language :: Python :: 3.7
Classifier: Programming Language :: Python :: 3.8
Classifier: Topic :: Scientific/Engineering
Classifier: Topic :: Scientific/Engineering :: Physics
Requires-Python: >=3.6
Requires-Dist: matplotlib
Requires-Dist: numpy
Requires-Dist: opt-einsum
Requires-Dist: PyYAML
Requires-Dist: scipy
Requires-Dist: sympy
Requires-Dist: tensorflow (<=2.2,>=2.0)
Provides-Extra: all
Requires-Dist: graphviz ; extra == 'all'
Requires-Dist: iminuit ; extra == 'all'
Requires-Dist: uproot3 ; extra == 'all'
Requires-Dist: Sphinx ; extra == 'all'
Requires-Dist: sphinx-rtd-theme ; extra == 'all'
Requires-Dist: sphinx-gallery ; extra == 'all'
Requires-Dist: pysnooper ; extra == 'all'
Requires-Dist: pytest ; extra == 'all'
Requires-Dist: pytest-benchmark ; extra == 'all'
Requires-Dist: pytest-cov ; extra == 'all'
Requires-Dist: black (==20.8b1) ; extra == 'all'
Requires-Dist: doc8 ; extra == 'all'
Requires-Dist: isort ; extra == 'all'
Requires-Dist: pre-commit ; extra == 'all'
Requires-Dist: pylint ; extra == 'all'
Requires-Dist: rstcheck ; extra == 'all'
Provides-Extra: dev
Requires-Dist: graphviz ; extra == 'dev'
Requires-Dist: iminuit ; extra == 'dev'
Requires-Dist: uproot3 ; extra == 'dev'
Requires-Dist: Sphinx ; extra == 'dev'
Requires-Dist: sphinx-rtd-theme ; extra == 'dev'
Requires-Dist: sphinx-gallery ; extra == 'dev'
Requires-Dist: pysnooper ; extra == 'dev'
Requires-Dist: pytest ; extra == 'dev'
Requires-Dist: pytest-benchmark ; extra == 'dev'
Requires-Dist: pytest-cov ; extra == 'dev'
Requires-Dist: black (==20.8b1) ; extra == 'dev'
Requires-Dist: doc8 ; extra == 'dev'
Requires-Dist: isort ; extra == 'dev'
Requires-Dist: pre-commit ; extra == 'dev'
Requires-Dist: pylint ; extra == 'dev'
Requires-Dist: rstcheck ; extra == 'dev'
Provides-Extra: doc
Requires-Dist: uproot3 ; extra == 'doc'
Requires-Dist: Sphinx ; extra == 'doc'
Requires-Dist: sphinx-rtd-theme ; extra == 'doc'
Requires-Dist: sphinx-gallery ; extra == 'doc'
Provides-Extra: gpu
Requires-Dist: tensorflow-gpu (<=2.2,>=2.0) ; extra == 'gpu'
Provides-Extra: minuit
Requires-Dist: iminuit ; extra == 'minuit'
Provides-Extra: root
Requires-Dist: uproot3 ; extra == 'root'
Provides-Extra: test
Requires-Dist: uproot3 ; extra == 'test'
Requires-Dist: pysnooper ; extra == 'test'
Requires-Dist: pytest ; extra == 'test'
Requires-Dist: pytest-benchmark ; extra == 'test'
Requires-Dist: pytest-cov ; extra == 'test'
Provides-Extra: vis
Requires-Dist: graphviz ; extra == 'vis'
